Workbook

Sheet Dashboard
A1: 🛡️ ENTERPRISE VULNERABILITY & DEPENDENCY COMMAND CENTER
A2: Last Updated: 2025-12-11 19:02:11 | Auto-Refresh Enabled
A4: 📊 KEY PERFORMANCE INDICATORS
A6: TOTAL VULNS | C6: CRITICAL | E6: HIGH | G6: MEDIUM | I6: LOW | K6: OPEN | M6: RESOLVED
A7: =COUNTA(Vulnerabilities!A:A)-1 -> 5 | C7: =COUNTIF(Vulnerabilities!E:E,"Critical") -> 4 | E7: =COUNTIF(Vulnerabilities!E:E,"High") -> 1 | G7: =COUNTIF(Vulnerabilities!E:E,"Medium") -> 0 | I7: =COUNTIF(Vulnerabilities!E:E,"Low") -> 0 | K7: =COUNTIF(Vulnerabilities!H:H,"Open") -> 3 | M7: =COUNTIF(Vulnerabilities!H:H,"Resolved") -> 1
A9: 📦 DEPENDENCY INTELLIGENCE
A11: TOTAL DEPS | C11: OUTDATED | E11: VULNERABLE | G11: UP-TO-DATE | I11: EOL RISK | K11: LICENSE RISK | M11: PROJECTS
A12: =COUNTA(Dependencies!A:A)-1 -> 8 | C12: =COUNTIF(Dependencies!G:G,"Outdated") -> 6 | E12: =COUNTIF(Dependencies!H:H,">0") -> 7 | G12: =COUNTIF(Dependencies!G:G,"Current") -> 1 | I12: =COUNTIF(Dependencies!I:I,"Yes") -> 1 | K12: =COUNTIF(Dependencies!K:K,"High") -> 0 | M12: =COUNTA(Projects!A:A)-1 -> 5
A14: 🎯 RISK POSTURE SCORE | H14: ⏱️ VULNERABILITY AGING
A16: OVERALL RISK SCORE | B16: =ROUND((COUNTIF(Vulnerabilities!E:E,"Critical")*10+COUNTIF(Vulnerabilities!E:E,"High")*7+COUNTIF(Vulnerabilities!E:E,"Medium")*4+COUNTIF(Vulnerabilities!E:E,"Low")*1)/(COUNTA(Vulnerabilities!A:A)-1+0.001)*10,1) -> 94 | H16: Age Bucket | I16: Count | J16: Critical | K16: High | L16: Medium | M16: Low
A17: MTTR (Days) | B17: =ROUND(AVERAGEIF(Vulnerabilities!H:H,"Resolved",Vulnerabilities!L:L),1) -> 0 | H17: 0-7 Days
A18: SLA Compliance % | B18: =ROUND(COUNTIF(Vulnerabilities!M:M,"Yes")/(COUNTA(Vulnerabilities!M:M)-1+0.001)*100,1)&"%" -> 60% | H18: 8-30 Days
H19: 31-90 Days
H20: 90+ Days
A21: 📈 MONTHLY TREND ANALYSIS
A23: Metric | B23: Jan | C23: Feb | D23: Mar | E23: Apr | F23: May | G23: Jun | H23: Jul | I23: Aug | J23: Sep | K23: Oct | L23: Nov | M23: Dec
A24: New Vulns | B24: 45 | C24: 42 | D24: 41 | E24: 30 | F24: 47 | G24: 29 | H24: 7 | I24: 13 | J24: 28 | K24: 42 | L24: 27 | M24: 45
A25: Resolved | B25: 17 | C25: 19 | D25: 42 | E25: 33 | F25: 20 | G25: 24 | H25: 31 | I25: 7 | J25: 34 | K25: 13 | L25: 5 | M25: 6
A26: Net Change | B26: =B24-C24 -> 3 | C26: =B24-C24 -> 3 | D26: =B24-C24 -> 3 | E26: =B24-C24 -> 3 | F26: =B24-C24 -> 3 | G26: =B24-C24 -> 3 | H26: =B24-C24 -> 3 | I26: =B24-C24 -> 3 | J26: =B24-C24 -> 3 | K26: =B24-C24 -> 3 | L26: =B24-C24 -> 3 | M26: =B24-C24 -> 3
A27: Critical Open | B27: 10 | C27: 4 | D27: 3 | E27: 10 | F27: 10 | G27: 8 | H27: 1 | I27: 2 | J27: 9 | K27: 8 | L27: 6 | M27: 2

Sheet Vulnerabilities
A1: Vuln ID | B1: CVE ID | C1: Title | D1: Description | E1: Severity | F1: CVSS Score | G1: CVSS Vector | H1: Status | I1: Affected Asset | J1: Asset Type | K1: Business Unit | L1: Days Open | M1: SLA Met | N1: Discovery Date | O1: Due Date | P1: Resolved Date | Q1: Assigned To | R1: Remediation Plan | S1: Exploitability | T1: Exploit Available | U1: Attack Vector | V1: CISA KEV | W1: EPSS Score | X1: Dependencies Affected | Y1: Projects Impacted | Z1: Risk Score | AA1: Priority Rank | AB1: Notes
A2: VULN-001 | B2: CVE-2024-21762 | C2: FortiOS Out-of-Bounds Write | D2: Remote code execution in FortiOS SSL VPN | E2: Critical | F2: 9.8 | G2: CVSS:3.1/AV:N/AC:L/PR:N/UI:N/S:U/C:H/I:H/A:H | H2: Open | I2: fw-prod-01.corp.local | J2: Firewall | K2: Infrastructure | L2: 45 | M2: No | N2: 2024-10-01 | O2: 2024-10-15 | Q2: John Smith | R2: Emergency patch scheduled | S2: High | T2: Yes | U2: Network | V2: Yes | W2: 0.97 | X2: N/A | Y2: ALL | Z2: 98 | AA2: 1 | AB2: Active exploitation in wild
A3: VULN-002 | B3: CVE-2024-3400 | C3: PAN-OS Command Injection | D3: GlobalProtect arbitrary code execution | E3: Critical | F3: 10 | G3: CVSS:3.1/AV:N/AC:L/PR:N/UI:N/S:C/C:H/I:H/A:H | H3: In Progress | I3: pan-gw-01.corp.local | J3: Firewall | K3: Infrastructure | L3: 30 | M3: No | N3: 2024-10-15 | O3: 2024-10-22 | Q3: Sarah Chen | R3: Hotfix deployment underway | S3: Critical | T3: Yes | U3: Network | V3: Yes | W3: 0.99 | X3: N/A | Y3: PROJ-001,PROJ-002 | Z3: 100 | AA3: 2 | AB3: State-sponsored exploitation
A4: VULN-003 | B4: CVE-2024-27198 | C4: TeamCity Auth Bypass | D4: Authentication bypass in JetBrains TeamCity | E4: Critical | F4: 9.8 | G4: CVSS:3.1/AV:N/AC:L/PR:N/UI:N/S:U/C:H/I:H/A:H | H4: Resolved | I4: teamcity.corp.local | J4: CI/CD | K4: DevOps | L4: 0 | M4: Yes | N4: 2024-09-20 | O4: 2024-09-27 | P4: 2024-09-25 | Q4: Mike Johnson | R4: Patched to 2023.11.4 | S4: High | T4: Yes | U4: Network | V4: Yes | W4: 0.94 | X4: N/A | Y4: PROJ-003 | Z4: 0 | AA4: 99 | AB4: Supply chain risk mitigated
A5: VULN-004 | B5: CVE-2024-1709 | C5: ConnectWise ScreenConnect Auth Bypass | D5: Path traversal to RCE | E5: Critical | F5: 10 | G5: CVSS:3.1/AV:N/AC:L/PR:N/UI:N/S:C/C:H/I:H/A:H | H5: Open | I5: rmm.corp.local | J5: RMM Tool | K5: IT Ops | L5: 15 | M5: Yes | N5: 2024-11-01 | O5: 2024-11-08 | Q5: Lisa Wang | R5: Vendor patch pending | S5: Critical | T5: Yes | U5: Network | V5: Yes | W5: 0.98 | X5: N/A | Y5: PROJ-001 | Z5: 95 | AA5: 3 | AB5: Ransomware vector
A6: VULN-005 | B6: CVE-2024-20353 | C6: Cisco ASA/FTD DoS | D6: Denial of service via HTTPS | E6: High | F6: 8.6 | G6: CVSS:3.1/AV:N/AC:L/PR:N/UI:N/S:C/C:N/I:N/A:H | H6: Open | I6: asa-dc-01.corp.local | J6: Firewall | K6: Infrastructure | L6: 20 | M6: Yes | N6: 2024-10-25 | O6: 2024-11-08 | Q6: Tom Brown | R6: Scheduled maintenance window | S6: Medium | T6: No | U6: Network | V6: No | W6: 0.45 | X6: N/A | Y6: PROJ-002 | Z6: 65 | AA6: 5 | AB6: Low exploit likelihood

Sheet Dependencies
A1: Dep ID | B1: Package Name | C1: Current Version | D1: Latest Version | E1: Latest Stable | F1: Version Gap | G1: Update Status | H1: Known Vulns | I1: EOL/Deprecated | J1: Release Date | K1: License | L1: License Risk | M1: Package Type | N1: Source Registry | O1: Direct/Transitive | P1: Used In Projects | Q1: Usage Count | R1: Last Scanned | S1: Update Priority | T1: Breaking Changes | U1: Migration Effort | V1: Owner/Maintainer | W1: Notes
A2: DEP-001 | B2: lodash | C2: 4.17.15 | D2: 4.17.21 | E2: 4.17.21 | F2: 6 | G2: Outdated | H2: 3 | I2: No | J2: 2019-07-19 | K2: MIT | L2: Low | M2: npm | N2: npmjs.com | O2: Direct | P2: PROJ-001,PROJ-002,PROJ-003 | Q2: 15 | R2: 2024-11-15 | S2: High | T2: No | U2: Low | V2: lodash | W2: Prototype pollution vulns
A3: DEP-002 | B3: log4j-core | C3: 2.14.1 | D3: 2.23.1 | E3: 2.23.1 | F3: 23 | G3: Critical | H3: 5 | I3: No | J3: 2021-03-06 | K3: Apache-2.0 | L3: Low | M3: maven | N3: maven-central | O3: Direct | P3: PROJ-004,PROJ-005 | Q3: 8 | R3: 2024-11-15 | S3: Critical | T3: Yes | U3: High | V3: Apache | W3: Log4Shell - IMMEDIATE ACTION
A4: DEP-003 | B4: spring-boot | C4: 2.7.18 | D4: 3.2.5 | E4: 3.2.5 | F4: 15 | G4: Outdated | H4: 2 | I4: No | J4: 2023-11-23 | K4: Apache-2.0 | L4: Low | M4: maven | N4: maven-central | O4: Direct | P4: PROJ-004 | Q4: 5 | R4: 2024-11-15 | S4: Medium | T4: Yes | U4: High | V4: VMware | W4: Major version upgrade needed
A5: DEP-004 | B5: moment | C5: 2.29.4 | D5: 2.30.1 | E5: 2.30.1 | F5: 1 | G5: Current | H5: 0 | I5: Yes | J5: 2022-07-06 | K5: MIT | L5: Low | M5: npm | N5: npmjs.com | O5: Direct | P5: PROJ-001,PROJ-002 | Q5: 12 | R5: 2024-11-15 | S5: Low | T5: No | U5: Medium | V5: moment | W5: Consider migration to dayjs
A6: DEP-005 | B6: requests | C6: 2.28.0 | D6: 2.31.0 | E6: 2.31.0 | F6: 3 | G6: Outdated | H6: 1 | I6: No | J6: 2022-06-09 | K6: Apache-2.0 | L6: Low | M6: pypi | N6: pypi.org | O6: Direct | P6: PROJ-006,PROJ-007 | Q6: 20 | R6: 2024-11-15 | S6: Medium | T6: No | U6: Low | V6: PSF | W6: SSL cert verification fix needed
A7: DEP-006 | B7: express | C7: 4.18.2 | D7: 4.19.2 | E7: 4.19.2 | F7: 2 | G7: Outdated | H7: 1 | I7: No | J7: 2023-02-24 | K7: MIT | L7: Low | M7: npm | N7: npmjs.com | O7: Direct | P7: PROJ-001,PROJ-002,PROJ-008 | Q7: 25 | R7: 2024-11-15 | S7: Medium | T7: No | U7: Low | V7: OpenJS | W7: Path traversal fix
A8: DEP-007 | B8: tensorflow | C8: 2.12.0 | D8: 2.16.1 | E8: 2.16.1 | F8: 8 | G8: Outdated | H8: 4 | I8: No | J8: 2023-03-22 | K8: Apache-2.0 | L8: Low | M8: pypi | N8: pypi.org | O8: Direct | P8: PROJ-009 | Q8: 3 | R8: 2024-11-15 | S8: High | T8: Yes | U8: High | V8: Google | W8: Multiple security patches
A9: DEP-008 | B9: jquery | C9: 3.5.1 | D9: 3.7.1 | E9: 3.7.1 | F9: 6 | G9: Outdated | H9: 2 | I9: No | J9: 2020-05-04 | K9: MIT | L9: Low | M9: npm | N9: npmjs.com | O9: Direct | P9: PROJ-010 | Q9: 8 | R9: 2024-11-15 | S9: Medium | T9: No | U9: Low | V9: OpenJS | W9: XSS vulnerabilities

Sheet Projects
A1: Project ID | B1: Project Name | C1: Business Unit | D1: Criticality | E1: Environment | F1: Tech Stack | G1: Total Dependencies | H1: Vulnerable Deps | I1: Outdated Deps | J1: Open Vulns | K1: Critical Vulns | L1: High Vulns | M1: Risk Score | N1: Last Scan | O1: Scan Frequency | P1: Owner | Q1: Security Contact | R1: Compliance Req | S1: Data Classification | T1: Internet Facing | U1: Status | V1: Notes
A2: PROJ-001 | B2: Customer Portal | C2: Sales | D2: Critical | E2: Production | F2: React, Node.js, PostgreSQL | G2: 45 | H2: 5 | I2: 12 | J2: 8 | K2: 2 | L2: 3 | M2: 85 | N2: 2024-11-15 | O2: Daily | P2: Jane Doe | Q2: security@corp.com | R2: SOC2, PCI-DSS | S2: Confidential | T2: Yes | U2: Active | V2: Primary revenue application
A3: PROJ-002 | B3: Internal Wiki | C3: IT | D3: Medium | E3: Production | F3: Python, Django, MySQL | G3: 28 | H3: 2 | I3: 5 | J3: 3 | K3: 0 | L3: 1 | M3: 45 | N3: 2024-11-14 | O3: Weekly | P3: Bob Smith | Q3: security@corp.com | R3: SOC2 | S3: Internal | T3: No | U3: Active | V3: Knowledge management
A4: PROJ-003 | B4: CI/CD Pipeline | C4: DevOps | D4: Critical | E4: Production | F4: Go, Docker, Kubernetes | G4: 67 | H4: 8 | I4: 15 | J4: 12 | K4: 3 | L4: 5 | M4: 92 | N4: 2024-11-15 | O4: Continuous | P4: Sarah Chen | Q4: security@corp.com | R4: SOC2 | S4: Restricted | T4: No | U4: Active | V4: Build infrastructure
A5: PROJ-004 | B5: Payment Service | C5: Finance | D5: Critical | E5: Production | F5: Java, Spring Boot, Oracle | G5: 52 | H5: 7 | I5: 10 | J5: 9 | K5: 2 | L5: 4 | M5: 88 | N5: 2024-11-15 | O5: Daily | P5: Mike Johnson | Q5: security@corp.com | R5: PCI-DSS, SOX | S5: Highly Confidential | T5: Yes | U5: Active | V5: Payment processing
A6: PROJ-005 | B6: Analytics Engine | C6: Data | D6: High | E6: Production | F6: Python, Spark, Kafka | G6: 89 | H6: 4 | I6: 20 | J6: 6 | K6: 1 | L6: 2 | M6: 65 | N6: 2024-11-14 | O6: Daily | P6: Lisa Wang | Q6: security@corp.com | R6: GDPR | S6: Confidential | T6: No | U6: Active | V6: Business intelligence

Sheet Risk Assessment
A1: 🎯 ENTERPRISE RISK ASSESSMENT MATRIX
A3: Risk ID | B3: Risk Category | C3: Risk Description | D3: Likelihood | E3: Impact | F3: Risk Score | G3: Risk Level | H3: Mitigation Strategy | I3: Owner | J3: Status | K3: Target Date | L3: Residual Risk | M3: Notes
A4: RISK-001 | B4: Supply Chain | C4: Compromised dependencies in production | D4: 4 | E4: 5 | F4: =D4*E4 -> 20 | G4: Critical | H4: SCA scanning, vendor vetting, SBOM | I4: CISO | J4: Open | K4: 2024-12-31 | L4: 8 | M4: Log4Shell class events
A5: RISK-002 | B5: Zero-Day | C5: Unpatched vulnerabilities exploitation | D5: 3 | E5: 5 | F5: =D5*E5 -> 15 | G5: High | H5: WAF, IDS/IPS, threat intel feeds | I5: SecOps Lead | J5: Monitoring | K5: Ongoing | L5: 10 | M5: Continuous monitoring required
A6: RISK-003 | B6: License Compliance | C6: GPL violation in proprietary code | D6: 2 | E6: 4 | F6: =D6*E6 -> 8 | G6: Medium | H6: License scanning, legal review | I6: Legal | J6: In Progress | K6: 2024-11-30 | L6: 4 | M6: Open source audit ongoing
A7: RISK-004 | B7: EOL Software | C7: Unsupported software in production | D7: 4 | E7: 4 | F7: =D7*E7 -> 16 | G7: High | H7: Inventory tracking, upgrade planning | I7: IT Ops | J7: Open | K7: 2025-01-31 | L7: 12 | M7: Legacy system migration
A8: RISK-005 | B8: Dependency Drift | C8: Version sprawl across projects | D8: 3 | E8: 3 | F8: =D8*E8 -> 9 | G8: Medium | H8: Centralized dep management, automation | I8: DevOps | J8: In Progress | K8: 2024-12-15 | L8: 6 | M8: Implementing Renovate
A11: 🔥 RISK HEAT MAP
A13: Impact → | B13: Negligible | C13: Minor | D13: Moderate | E13: Major | F13: Catastrophic
A14: Almost Certain
A15: Likely
A16: Possible
A17: Unlikely
A18: Rare

Sheet Remediation
A1: Task ID | B1: Related Vuln/Dep | C1: Task Description | D1: Priority | E1: Assigned To | F1: Team | G1: Status | H1: Progress % | I1: Created Date | J1: Due Date | K1: Completed Date | L1: Blockers | M1: Dependencies | N1: Effort (Hours) | O1: Actual Hours | P1: Notes
A2: REM-001 | B2: VULN-001 | C2: Apply FortiOS emergency patch | D2: P1-Critical | E2: John Smith | F2: Infrastructure | G2: In Progress | H2: 75 | I2: 2024-11-01 | J2: 2024-11-08 | L2: Change window approval | M2: VULN-002 | N2: 8 | O2: 6 | P2: Weekend maintenance
A3: REM-002 | B3: VULN-002 | C3: Deploy PAN-OS hotfix | D3: P1-Critical | E3: Sarah Chen | F3: Infrastructure | G3: In Progress | H3: 50 | I3: 2024-11-05 | J3: 2024-11-10 | L3: Vendor support ticket | N3: 12 | O3: 4 | P3: Waiting vendor
A4: REM-003 | B4: DEP-002 | C4: Upgrade Log4j to 2.23.1 | D4: P1-Critical | E4: Mike Johnson | F4: Development | G4: Open | H4: 0 | I4: 2024-11-10 | J4: 2024-11-15 | L4: Testing environment | M4: REM-005 | N4: 24 | O4: 0 | P4: Requires Spring upgrade
A5: REM-004 | B5: DEP-001 | C5: Update lodash across all projects | D5: P2-High | E5: Dev Team | F5: Development | G5: Completed | H5: 100 | I5: 2024-10-15 | J5: 2024-10-25 | K5: 2024-10-23 | N5: 16 | O5: 12 | P5: Automated via Renovate
A6: REM-005 | B6: DEP-003 | C6: Spring Boot 2.x to 3.x migration | D6: P2-High | E6: Backend Team | F6: Development | G6: In Progress | H6: 30 | I6: 2024-10-01 | J6: 2024-12-31 | L6: Java 17 upgrade first | N6: 120 | O6: 36 | P6: Major refactoring

Sheet Compliance
A1: 📋 COMPLIANCE FRAMEWORK MAPPING
A3: Control ID | B3: Framework | C3: Control Family | D3: Control Description | E3: Implementation Status | F3: Evidence | G3: Related Vulns | H3: Gap Analysis | I3: Remediation Required | J3: Owner | K3: Last Assessed | L3: Next Review | M3: Notes
A4: NIST-SI-2 | B4: NIST CSF | C4: System & Info Integrity | D4: Flaw Remediation | E4: Partial | F4: Vuln scan reports | G4: VULN-001,VULN-002 | H4: SLA compliance 85% | I4: Yes | J4: SecOps | K4: 2024-11-01 | L4: 2024-12-01 | M4: Patch management gaps
A5: NIST-CM-8 | B5: NIST CSF | C5: Config Management | D5: Information System Component Inventory | E5: Implemented | F5: CMDB exports | H5: Fully compliant | I5: No | J5: IT Ops | K5: 2024-10-15 | L5: 2025-01-15 | M5: Automated discovery
A6: PCI-6.2 | B6: PCI-DSS | C6: Secure Systems | D6: Protect from Known Vulnerabilities | E6: Partial | F6: Scan evidence | G6: VULN-003,VULN-004 | H6: Critical patches pending | I6: Yes | J6: Compliance | K6: 2024-11-05 | L6: 2024-11-20 | M6: Payment scope
A7: SOC2-CC6.1 | B7: SOC2 | C7: Logical Access | D7: Security Software Implementation | E7: Implemented | F7: WAF logs, IDS alerts | H7: Meets criteria | I7: No | J7: Security | K7: 2024-10-01 | L7: 2025-01-01 | M7: Annual audit passed
A8: CIS-2.1 | B8: CIS Controls | C8: Software Inventory | D8: Maintain Software Inventory | E8: Partial | F8: SCA tool output | G8: DEP-001-008 | H8: 92% coverage | I8: Yes | J8: DevOps | K8: 2024-11-10 | L8: 2024-12-10 | M8: SBOM implementation

Sheet Vendor Risk
A1: Vendor ID | B1: Vendor Name | C1: Product/Service | D1: Criticality | E1: Data Access | F1: Security Rating | G1: Last Assessment | H1: Next Assessment | I1: Contract Expiry | J1: SLA Score | K1: Incident History | L1: Certifications | M1: Risk Tier | N1: Status | O1: Notes
A2: VEN-001 | B2: Fortinet | C2: FortiGate Firewall | D2: Critical | E2: Network Traffic | F2: B+ | G2: 2024-09-15 | H2: 2025-03-15 | I2: 2025-12-31 | J2: 95 | K2: 1 | L2: SOC2, ISO27001 | M2: Tier 1 | N2: Active | O2: Critical vulnerability disclosed
A3: VEN-002 | B3: Palo Alto Networks | C3: NGFW | D3: Critical | E3: Network Traffic | F3: A- | G3: 2024-10-01 | H3: 2025-04-01 | I3: 2026-06-30 | J3: 98 | K3: 0 | L3: SOC2, FedRAMP | M3: Tier 1 | N3: Active | O3: GlobalProtect CVE
A4: VEN-003 | B4: JetBrains | C4: TeamCity | D4: High | E4: Source Code | F4: B | G4: 2024-08-01 | H4: 2025-02-01 | I4: 2025-08-31 | J4: 88 | K4: 2 | L4: SOC2 | M4: Tier 2 | N4: Under Review | O4: Auth bypass history
A5: VEN-004 | B5: Lodash (OSS) | C5: Utility Library | D5: Medium | E5: None | F5: C+ | G5: 2024-11-01 | H5: 2025-05-01 | I5: N/A | J5: N/A | K5: 3 | L5: N/A | M5: Tier 3 | N5: Active | O5: Community maintained
A6: VEN-005 | B6: Apache Foundation | C6: Log4j | D6: Critical | E6: Application Logs | F6: A | G6: 2024-11-15 | H6: 2025-05-15 | I6: N/A | J6: N/A | K6: 1 | L6: N/A | M6: Tier 1 | N6: Monitoring | O6: Log4Shell remediation complete

Sheet Config
A1: ⚙️ CONFIGURATION & REFERENCE DATA
A3: Severity Levels
A4: Level | B4: CVSS Range | C4: SLA Target | D4: Color
A5: Critical | B5: CVSS 9.0-10.0 | C5: 24 hours
A6: High | B6: CVSS 7.0-8.9 | C6: 7 days
A7: Medium | B7: CVSS 4.0-6.9 | C7: 30 days
A8: Low | B8: CVSS 0.1-3.9 | C8: 90 days
A9: Informational | B9: CVSS 0.0 | C9: Best effort
A12: Status Values
A13: Status | B13: Description
A14: Open | B14: New vulnerability identified, awaiting triage
A15: In Progress | B15: Remediation actively being worked
A16: Resolved | B16: Vulnerability has been patched/mitigated
A17: Accepted | B17: Risk accepted with compensating controls
A18: Deferred | B18: Remediation scheduled for future date
A21: Priority Levels
A22: Priority | B22: Description | C22: Response Time
A23: P1-Critical | B23: Immediate action required | C23: 4 hours
A24: P2-High | B24: Address within sprint | C24: 24 hours
A25: P3-Medium | B25: Schedule for next release | C25: 1 week
A26: P4-Low | B26: Backlog item | C26: 1 month
